hfdl/__init__.py
hfdl/cli.py
hfdl/config.py
hfdl/config_mixins.py
hfdl/downloader.py
hfdl/file_manager.py
hfdl/speed_manager.py
hfdl/thread_manager.py
hfdl/utils.py
hfdl/validation.py
hfdl/tests/__init__.py
hfdl/tests/conftest.py
hfdl/tests/test_cli.py
hfdl/tests/test_downloader.py
hfdl/tests/test_file_manager.py
hfdl/tests/test_speed_manager.py
hfdl/tests/test_thread_manager.py
hfdl/tests/test_utils.py
hfdl-0.4.0.dist-info/LICENSE
hfdl-0.4.0.dist-info/METADATA
hfdl-0.4.0.dist-info/WHEEL
hfdl-0.4.0.dist-info/entry_points.txt
hfdl-0.4.0.dist-info/top_level.txt
hfdl-0.4.0.dist-info/RECORD
