Metadata-Version: 2.2
Name: hfdl
Version: 0.4.0
Summary: Fast and reliable downloader for Hugging Face models and datasets
Home-page: https://github.com/MubarakHAlketbi/hfdl
Author: Mubarak H. Alketbi
Author-email: mubarak.harran@gmail.com
Project-URL: Bug Reports, https://github.com/MubarakHAlketbi/hfdl/issues
Project-URL: Source, https://github.com/MubarakHAlketbi/hfdl
Keywords: huggingface download models datasets machine-learning
Classifier: Development Status :: 3 - Alpha
Classifier: Intended Audience :: Developers
Classifier: Intended Audience :: Science/Research
Classifier: License :: OSI Approved :: MIT License
Classifier: Operating System :: OS Independent
Classifier: Programming Language :: Python :: 3
Classifier: Programming Language :: Python :: 3.10
Classifier: Programming Language :: Python :: 3.11
Classifier: Topic :: Scientific/Engineering :: Artificial Intelligence
Classifier: Topic :: Software Development :: Libraries :: Python Modules
Requires-Python: >=3.10
License-File: LICENSE
Requires-Dist: huggingface_hub>=0.28.1
Requires-Dist: tqdm>=4.67.1
Requires-Dist: pydantic>=2.10.6
Requires-Dist: requests>=2.32.3
Provides-Extra: test
Requires-Dist: pytest>=8.3.4; extra == "test"
Requires-Dist: pytest-mock>=3.14.0; extra == "test"
Requires-Dist: types-requests>=2.32.0; extra == "test"
Requires-Dist: types-tqdm>=4.67.0; extra == "test"
Provides-Extra: dev
Requires-Dist: pytest>=8.3.4; extra == "dev"
Requires-Dist: pytest-mock>=3.14.0; extra == "dev"
Requires-Dist: types-requests>=2.32.0; extra == "dev"
Requires-Dist: types-tqdm>=4.67.0; extra == "dev"
Requires-Dist: black>=25.1.0; extra == "dev"
Requires-Dist: isort>=6.0.0; extra == "dev"
Requires-Dist: mypy>=1.15.0; extra == "dev"
Requires-Dist: flake8>=7.1.1; extra == "dev"
Dynamic: author
Dynamic: author-email
Dynamic: classifier
Dynamic: description
Dynamic: description-content-type
Dynamic: home-page
Dynamic: keywords
Dynamic: project-url
Dynamic: provides-extra
Dynamic: requires-dist
Dynamic: requires-python
Dynamic: summary
